Metadata-Version: 1.1
Name: quali-testing-helpers
Version: 1.0.0
Summary: Helpers and utilities for tests
Home-page: https://github.com/QualiSystems/quali-test-helpers
Author: Quali
Author-email: info@quali.com
License: Apache 2.0
Keywords: testing unitests utilities
Platform: UNKNOWN
Classifier: Development Status :: 5 - Production/Stable
Classifier: Programming Language :: Python :: 2.7
Classifier: Topic :: Software Development :: Libraries
Classifier: License :: OSI Approved :: Apache Software License
